workforce_async/__init__.py
workforce_async/aiohttp.py
workforce_async/models.py
workforce_async-0.12.0.dist-info/LICENSE
workforce_async-0.12.0.dist-info/WHEEL
workforce_async-0.12.0.dist-info/METADATA
workforce_async-0.12.0.dist-info/RECORD
