Metadata-Version: 2.1
Name: workforce-async
Version: 0.12.0
Summary: Asyncio Wrapper
Home-page: https://github.com/Kick1911/WorkForce
Keywords: asyncio,tasks,framework
Author: Caswall Engelsman
Author-email: mail@cengelsman.com
Requires-Python: >=3.6,<4.0
Classifier: Development Status :: 2 - Pre-Alpha
Classifier: Programming Language :: Python :: 3
Classifier: Programming Language :: Python :: 3.10
Classifier: Programming Language :: Python :: 3.6
Classifier: Programming Language :: Python :: 3.7
Classifier: Programming Language :: Python :: 3.8
Classifier: Programming Language :: Python :: 3.9
Classifier: Topic :: Software Development :: Libraries :: Python Modules
Requires-Dist: aiohttp (>=3.7.4,<4.0.0)
Project-URL: Bug Tracker, https://github.com/Kick1911/WorkForce/issues
Project-URL: Repository, https://github.com/Kick1911/WorkForce
